minecraftTellrawGenerator/__init__.py
minecraftTellrawGenerator-1.0.5.dist-info/DESCRIPTION.rst
minecraftTellrawGenerator-1.0.5.dist-info/METADATA
minecraftTellrawGenerator-1.0.5.dist-info/RECORD
minecraftTellrawGenerator-1.0.5.dist-info/WHEEL
minecraftTellrawGenerator-1.0.5.dist-info/metadata.json
minecraftTellrawGenerator-1.0.5.dist-info/top_level.txt
