Metadata-Version: 2.0
Name: minecraftTellrawGenerator
Version: 1.0.5
Summary: Easily create minecraft tellraw command
Home-page: https://github.com/MyTheValentinus/minecraftTellrawGenerator
Author: Valentin DEVILLE
Author-email: contact@valentin-deville.eu
License: UNKNOWN
Project-URL: Bug Reports, https://github.com/MyTheValentinus/minecraftTellrawGenerator/issues
Project-URL: Donation, https://www.paypal.me/ValentinDeville
Project-URL: Source, https://github.com/MyTheValentinus/minecraftTellrawGenerator
Keywords: minecraft tellraw command
Platform: UNKNOWN
Classifier: Development Status :: 5 - Production/Stable
Classifier: Intended Audience :: Developers
Classifier: Intended Audience :: System Administrators
Classifier: Topic :: Software Development :: Build Tools
Classifier: Natural Language :: French
Classifier: Programming Language :: Python :: 3 :: Only
Classifier: Topic :: Utilities
Requires-Python: >=3
